[{"Name":"pull-ci-openshift-ovn-kubernetes-master-4.15-upgrade-from-stable-4.14-e2e-aws-ovn-upgrade","AlwaysRun":true,"Optional":false,"SuccessCount":27,"FailureCount":24,"AbortedCount":7,"PendingCount":2,"ErrorCount":0,"PassRate":0.5294117647058824,"TotalJobCount":60},{"Name":"pull-ci-openshift-ovn-kubernetes-master-4.15-upgrade-from-stable-4.14-local-gateway-e2e-aws-ovn-upgrade","AlwaysRun":true,"Optional":false,"SuccessCount":27,"FailureCount":25,"AbortedCount":6,"PendingCount":2,"ErrorCount":0,"PassRate":0.5192307692307693,"TotalJobCount":60},{"Name":"pull-ci-openshift-ovn-kubernetes-master-e2e-aws-ovn","AlwaysRun":true,"Optional":false,"SuccessCount":33,"FailureCount":21,"AbortedCount":5,"PendingCount":1,"ErrorCount":0,"PassRate":0.6111111111111112,"TotalJobCount":60},{"Name":"pull-ci-openshift-ovn-kubernetes-master-e2e-aws-ovn-hypershift","AlwaysRun":true,"Optional":false,"SuccessCount":43,"FailureCount":10,"AbortedCount":6,"PendingCount":1,"ErrorCount":0,"PassRate":0.8113207547169812,"TotalJobCount":60},{"Name":"pull-ci-openshift-ovn-kubernetes-master-e2e-aws-ovn-kubevirt","AlwaysRun":true,"Optional":true,"SuccessCount":8,"FailureCount":41,"AbortedCount":10,"PendingCount":1,"ErrorCount":0,"PassRate":0.16326530612244897,"TotalJobCount":60},{"Name":"pull-ci-openshift-ovn-kubernetes-master-e2e-aws-ovn-local-gateway","AlwaysRun":true,"Optional":false,"SuccessCount":32,"FailureCount":21,"AbortedCount":6,"PendingCount":1,"ErrorCount":0,"PassRate":0.6037735849056604,"TotalJobCount":60},{"Name":"pull-ci-openshift-ovn-kubernetes-master-e2e-aws-ovn-local-to-shared-gateway-mode-migration","AlwaysRun":true,"Optional":false,"SuccessCount":32,"FailureCount":22,"AbortedCount":5,"PendingCount":1,"ErrorCount":0,"PassRate":0.5925925925925926,"TotalJobCount":60},{"Name":"pull-ci-openshift-ovn-kubernetes-master-e2e-aws-ovn-serial","AlwaysRun":true,"Optional":false,"SuccessCount":31,"FailureCount":24,"AbortedCount":5,"PendingCount":0,"ErrorCount":0,"PassRate":0.5636363636363636,"TotalJobCount":60},{"Name":"pull-ci-openshift-ovn-kubernetes-master-e2e-aws-ovn-shared-to-local-gateway-mode-migration","AlwaysRun":true,"Optional":false,"SuccessCount":31,"FailureCount":23,"AbortedCount":5,"PendingCount":1,"ErrorCount":0,"PassRate":0.5740740740740741,"TotalJobCount":60},{"Name":"pull-ci-openshift-ovn-kubernetes-master-e2e-aws-ovn-upgrade","AlwaysRun":true,"Optional":false,"SuccessCount":26,"FailureCount":25,"AbortedCount":7,"PendingCount":2,"ErrorCount":0,"PassRate":0.5098039215686274,"TotalJobCount":60},{"Name":"pull-ci-openshift-ovn-kubernetes-master-e2e-aws-ovn-upgrade-local-gateway","AlwaysRun":true,"Optional":false,"SuccessCount":27,"FailureCount":24,"AbortedCount":7,"PendingCount":2,"ErrorCount":0,"PassRate":0.5294117647058824,"TotalJobCount":60},{"Name":"pull-ci-openshift-ovn-kubernetes-master-e2e-aws-ovn-windows","AlwaysRun":true,"Optional":false,"SuccessCount":34,"FailureCount":19,"AbortedCount":7,"PendingCount":0,"ErrorCount":0,"PassRate":0.6415094339622641,"TotalJobCount":60},{"Name":"pull-ci-openshift-ovn-kubernetes-master-e2e-azure-ovn","AlwaysRun":true,"Optional":true,"SuccessCount":42,"FailureCount":11,"AbortedCount":7,"PendingCount":0,"ErrorCount":0,"PassRate":0.7924528301886793,"TotalJobCount":60},{"Name":"pull-ci-openshift-ovn-kubernetes-master-e2e-gcp-ovn","AlwaysRun":true,"Optional":false,"SuccessCount":42,"FailureCount":11,"AbortedCount":6,"PendingCount":1,"ErrorCount":0,"PassRate":0.7924528301886793,"TotalJobCount":60},{"Name":"pull-ci-openshift-ovn-kubernetes-master-e2e-metal-ipi-ovn-dualstack","AlwaysRun":true,"Optional":false,"SuccessCount":29,"FailureCount":20,"AbortedCount":10,"PendingCount":1,"ErrorCount":0,"PassRate":0.5918367346938775,"TotalJobCount":60},{"Name":"pull-ci-openshift-ovn-kubernetes-master-e2e-metal-ipi-ovn-ipv6","AlwaysRun":true,"Optional":false,"SuccessCount":10,"FailureCount":47,"AbortedCount":2,"PendingCount":1,"ErrorCount":0,"PassRate":0.17543859649122806,"TotalJobCount":60},{"Name":"pull-ci-openshift-ovn-kubernetes-master-e2e-openstack-ovn","AlwaysRun":true,"Optional":true,"SuccessCount":20,"FailureCount":29,"AbortedCount":9,"PendingCount":1,"ErrorCount":1,"PassRate":0.40816326530612246,"TotalJobCount":60},{"Name":"pull-ci-openshift-ovn-kubernetes-master-e2e-ovn-hybrid-step-registry","AlwaysRun":true,"Optional":true,"SuccessCount":34,"FailureCount":20,"AbortedCount":6,"PendingCount":0,"ErrorCount":0,"PassRate":0.6296296296296297,"TotalJobCount":60},{"Name":"pull-ci-openshift-ovn-kubernetes-master-e2e-vsphere-ovn","AlwaysRun":true,"Optional":true,"SuccessCount":19,"FailureCount":32,"AbortedCount":8,"PendingCount":1,"ErrorCount":0,"PassRate":0.37254901960784315,"TotalJobCount":60},{"Name":"pull-ci-openshift-ovn-kubernetes-master-e2e-vsphere-windows","AlwaysRun":true,"Optional":false,"SuccessCount":39,"FailureCount":13,"AbortedCount":8,"PendingCount":0,"ErrorCount":0,"PassRate":0.75,"TotalJobCount":60},{"Name":"pull-ci-openshift-ovn-kubernetes-master-okd-e2e-gcp-ovn","AlwaysRun":true,"Optional":true,"SuccessCount":32,"FailureCount":24,"AbortedCount":4,"PendingCount":0,"ErrorCount":0,"PassRate":0.5714285714285714,"TotalJobCount":60}]