[{"Name":"pull-ci-openshift-cluster-network-operator-master-4.16-upgrade-from-stable-4.15-e2e-aws-ovn-upgrade","AlwaysRun":true,"Optional":true,"SuccessCount":20,"FailureCount":7,"AbortedCount":33,"PendingCount":0,"ErrorCount":0,"UnknownCount":0,"PassRate":0.7407407407407407,"TotalJobCount":60},{"Name":"pull-ci-openshift-cluster-network-operator-master-4.16-upgrade-from-stable-4.15-e2e-azure-ovn-upgrade","AlwaysRun":true,"Optional":true,"SuccessCount":13,"FailureCount":12,"AbortedCount":35,"PendingCount":0,"ErrorCount":0,"UnknownCount":0,"PassRate":0.52,"TotalJobCount":60},{"Name":"pull-ci-openshift-cluster-network-operator-master-4.16-upgrade-from-stable-4.15-e2e-gcp-ovn-upgrade","AlwaysRun":true,"Optional":true,"SuccessCount":16,"FailureCount":10,"AbortedCount":34,"PendingCount":0,"ErrorCount":0,"UnknownCount":0,"PassRate":0.6153846153846154,"TotalJobCount":60},{"Name":"pull-ci-openshift-cluster-network-operator-master-e2e-aws-hypershift-ovn-kubevirt","AlwaysRun":true,"Optional":true,"SuccessCount":12,"FailureCount":17,"AbortedCount":31,"PendingCount":0,"ErrorCount":0,"UnknownCount":0,"PassRate":0.41379310344827586,"TotalJobCount":60},{"Name":"pull-ci-openshift-cluster-network-operator-master-e2e-aws-live-migration-sdn-ovn","AlwaysRun":true,"Optional":false,"SuccessCount":20,"FailureCount":14,"AbortedCount":26,"PendingCount":0,"ErrorCount":0,"UnknownCount":0,"PassRate":0.5882352941176471,"TotalJobCount":60},{"Name":"pull-ci-openshift-cluster-network-operator-master-e2e-aws-live-migration-sdn-ovn-rollback","AlwaysRun":true,"Optional":true,"SuccessCount":14,"FailureCount":17,"AbortedCount":29,"PendingCount":0,"ErrorCount":0,"UnknownCount":0,"PassRate":0.45161290322580644,"TotalJobCount":60},{"Name":"pull-ci-openshift-cluster-network-operator-master-e2e-aws-ovn-local-to-shared-gateway-mode-migration","AlwaysRun":true,"Optional":true,"SuccessCount":22,"FailureCount":9,"AbortedCount":29,"PendingCount":0,"ErrorCount":0,"UnknownCount":0,"PassRate":0.7096774193548387,"TotalJobCount":60},{"Name":"pull-ci-openshift-cluster-network-operator-master-e2e-aws-ovn-network-migration","AlwaysRun":true,"Optional":false,"SuccessCount":20,"FailureCount":15,"AbortedCount":25,"PendingCount":0,"ErrorCount":0,"UnknownCount":0,"PassRate":0.5714285714285714,"TotalJobCount":60},{"Name":"pull-ci-openshift-cluster-network-operator-master-e2e-aws-ovn-serial","AlwaysRun":true,"Optional":true,"SuccessCount":16,"FailureCount":13,"AbortedCount":31,"PendingCount":0,"ErrorCount":0,"UnknownCount":0,"PassRate":0.5517241379310345,"TotalJobCount":60},{"Name":"pull-ci-openshift-cluster-network-operator-master-e2e-aws-ovn-shared-to-local-gateway-mode-migration","AlwaysRun":true,"Optional":true,"SuccessCount":22,"FailureCount":9,"AbortedCount":29,"PendingCount":0,"ErrorCount":0,"UnknownCount":0,"PassRate":0.7096774193548387,"TotalJobCount":60},{"Name":"pull-ci-openshift-cluster-network-operator-master-e2e-aws-ovn-single-node","AlwaysRun":true,"Optional":true,"SuccessCount":10,"FailureCount":20,"AbortedCount":30,"PendingCount":0,"ErrorCount":0,"UnknownCount":0,"PassRate":0.3333333333333333,"TotalJobCount":60},{"Name":"pull-ci-openshift-cluster-network-operator-master-e2e-aws-ovn-windows","AlwaysRun":true,"Optional":false,"SuccessCount":24,"FailureCount":9,"AbortedCount":27,"PendingCount":0,"ErrorCount":0,"UnknownCount":0,"PassRate":0.7272727272727273,"TotalJobCount":60},{"Name":"pull-ci-openshift-cluster-network-operator-master-e2e-aws-sdn-upgrade","AlwaysRun":true,"Optional":true,"SuccessCount":18,"FailureCount":11,"AbortedCount":31,"PendingCount":0,"ErrorCount":0,"UnknownCount":0,"PassRate":0.6206896551724138,"TotalJobCount":60},{"Name":"pull-ci-openshift-cluster-network-operator-master-e2e-azure-ovn","AlwaysRun":true,"Optional":true,"SuccessCount":20,"FailureCount":10,"AbortedCount":30,"PendingCount":0,"ErrorCount":0,"UnknownCount":0,"PassRate":0.6666666666666666,"TotalJobCount":60},{"Name":"pull-ci-openshift-cluster-network-operator-master-e2e-gcp-ovn","AlwaysRun":true,"Optional":false,"SuccessCount":20,"FailureCount":17,"AbortedCount":23,"PendingCount":0,"ErrorCount":0,"UnknownCount":0,"PassRate":0.5405405405405406,"TotalJobCount":60},{"Name":"pull-ci-openshift-cluster-network-operator-master-e2e-gcp-ovn-upgrade","AlwaysRun":true,"Optional":false,"SuccessCount":16,"FailureCount":19,"AbortedCount":25,"PendingCount":0,"ErrorCount":0,"UnknownCount":0,"PassRate":0.45714285714285713,"TotalJobCount":60},{"Name":"pull-ci-openshift-cluster-network-operator-master-e2e-hypershift-ovn","AlwaysRun":true,"Optional":false,"SuccessCount":19,"FailureCount":18,"AbortedCount":23,"PendingCount":0,"ErrorCount":0,"UnknownCount":0,"PassRate":0.5135135135135135,"TotalJobCount":60},{"Name":"pull-ci-openshift-cluster-network-operator-master-e2e-metal-ipi-ovn-ipv6","AlwaysRun":true,"Optional":false,"SuccessCount":16,"FailureCount":19,"AbortedCount":25,"PendingCount":0,"ErrorCount":0,"UnknownCount":0,"PassRate":0.45714285714285713,"TotalJobCount":60},{"Name":"pull-ci-openshift-cluster-network-operator-master-e2e-metal-ipi-ovn-ipv6-ipsec","AlwaysRun":true,"Optional":true,"SuccessCount":9,"FailureCount":19,"AbortedCount":32,"PendingCount":0,"ErrorCount":0,"UnknownCount":0,"PassRate":0.32142857142857145,"TotalJobCount":60},{"Name":"pull-ci-openshift-cluster-network-operator-master-e2e-network-mtu-migration-ovn-ipv4","AlwaysRun":true,"Optional":true,"SuccessCount":13,"FailureCount":13,"AbortedCount":34,"PendingCount":0,"ErrorCount":0,"UnknownCount":0,"PassRate":0.5,"TotalJobCount":60},{"Name":"pull-ci-openshift-cluster-network-operator-master-e2e-network-mtu-migration-ovn-ipv6","AlwaysRun":true,"Optional":true,"SuccessCount":0,"FailureCount":27,"AbortedCount":33,"PendingCount":0,"ErrorCount":0,"UnknownCount":0,"PassRate":0,"TotalJobCount":60},{"Name":"pull-ci-openshift-cluster-network-operator-master-e2e-openstack-ovn","AlwaysRun":true,"Optional":true,"SuccessCount":15,"FailureCount":16,"AbortedCount":29,"PendingCount":0,"ErrorCount":0,"UnknownCount":0,"PassRate":0.4838709677419355,"TotalJobCount":60},{"Name":"pull-ci-openshift-cluster-network-operator-master-e2e-ovn-hybrid-step-registry","AlwaysRun":true,"Optional":true,"SuccessCount":23,"FailureCount":8,"AbortedCount":29,"PendingCount":0,"ErrorCount":0,"UnknownCount":0,"PassRate":0.7419354838709677,"TotalJobCount":60},{"Name":"pull-ci-openshift-cluster-network-operator-master-e2e-ovn-ipsec-step-registry","AlwaysRun":true,"Optional":true,"SuccessCount":16,"FailureCount":15,"AbortedCount":29,"PendingCount":0,"ErrorCount":0,"UnknownCount":0,"PassRate":0.5161290322580645,"TotalJobCount":60},{"Name":"pull-ci-openshift-cluster-network-operator-master-e2e-ovn-step-registry","AlwaysRun":true,"Optional":true,"SuccessCount":22,"FailureCount":9,"AbortedCount":29,"PendingCount":0,"ErrorCount":0,"UnknownCount":0,"PassRate":0.7096774193548387,"TotalJobCount":60},{"Name":"pull-ci-openshift-cluster-network-operator-master-e2e-vsphere-ovn","AlwaysRun":true,"Optional":true,"SuccessCount":21,"FailureCount":9,"AbortedCount":30,"PendingCount":0,"ErrorCount":0,"UnknownCount":0,"PassRate":0.7,"TotalJobCount":60},{"Name":"pull-ci-openshift-cluster-network-operator-master-e2e-vsphere-ovn-dualstack","AlwaysRun":true,"Optional":true,"SuccessCount":13,"FailureCount":19,"AbortedCount":28,"PendingCount":0,"ErrorCount":0,"UnknownCount":0,"PassRate":0.40625,"TotalJobCount":60},{"Name":"pull-ci-openshift-cluster-network-operator-master-e2e-vsphere-ovn-dualstack-primaryv6","AlwaysRun":true,"Optional":true,"SuccessCount":0,"FailureCount":31,"AbortedCount":29,"PendingCount":0,"ErrorCount":0,"UnknownCount":0,"PassRate":0,"TotalJobCount":60}]